{
  "project_info": {
    "project_number": "544287871390",
    "project_id": "kotlin-messenger-83d77",
    "storage_bucket": "kotlin-messenger-83d77.appspot.com"
  },
  "client": [
    {
      "client_info": {
        "mobilesdk_app_id": "1:544287871390:android:7541d2b40b68d93476868f",
        "android_client_info": {
          "package_name": "com.example.kotlinsoc"
        }
      },
      "oauth_client": [],
      "api_key": [
        {
          "current_key": "AIzaSyB7Jxqkcqk3BoWXI6DoW3ikG9qyf92ya4E"
        }
      ],
      "services": {
        "appinvite_service": {
          "other_platform_oauth_client": []
        }
      }
    }
  ],
  "configuration_version": "1"
}